azure/mgmt/relay/__init__.py
azure/mgmt/relay/_configuration.py
azure/mgmt/relay/_relay_api.py
azure/mgmt/relay/_version.py
azure/mgmt/relay/aio/__init__.py
azure/mgmt/relay/aio/_configuration.py
azure/mgmt/relay/aio/_relay_api.py
azure/mgmt/relay/aio/operations/__init__.py
azure/mgmt/relay/aio/operations/_hybrid_connections_operations.py
azure/mgmt/relay/aio/operations/_namespaces_operations.py
azure/mgmt/relay/aio/operations/_operations.py
azure/mgmt/relay/aio/operations/_wcf_relays_operations.py
azure/mgmt/relay/models/__init__.py
azure/mgmt/relay/models/_models.py
azure/mgmt/relay/models/_models_py3.py
azure/mgmt/relay/models/_relay_api_enums.py
azure/mgmt/relay/operations/__init__.py
azure/mgmt/relay/operations/_hybrid_connections_operations.py
azure/mgmt/relay/operations/_namespaces_operations.py
azure/mgmt/relay/operations/_operations.py
azure/mgmt/relay/operations/_wcf_relays_operations.py
azure_mgmt_relay-1.1.0.dist-info/METADATA
azure_mgmt_relay-1.1.0.dist-info/WHEEL
azure_mgmt_relay-1.1.0.dist-info/top_level.txt
azure_mgmt_relay-1.1.0.dist-info/RECORD
